<?xml version="1.0" encoding="UTF-8" standalone="no"?>
<!DOCTYPE openshot-effect>
<effect>
	<title translatable="True">Saturation</title>
	<description translatable="True">Adjusts the saturation or intensity of the image</description>
	<icon>saturate.png</icon>
	<category>Video</category>
	<service>frei0r.saturat0r</service>
	
	<param name="Saturation" type="hscale" title="Saturation" description="">
		<min>0.0</min>
		<max>1.0</max>
		<step>0.01</step>
		<default>0.5</default>
	</param>

</effect>

